{
    "priority_areas": [
        {
            "title": "Education Access",
            "description": "Improve access to quality education for all students, focusing on underserved communities."
        },
        {
            "title": "Digital Literacy",
            "description": "Enhance digital skills training programs to prepare students for the modern workforce."
        }
    ],
    "support_measures": [
        {
            "title": "Teacher Training",
            "description": "Implement comprehensive professional development programs for educators."
        },
        {
            "title": "Resource Allocation",
            "description": "Optimize resource distribution to ensure equitable access to educational materials."
        }
    ],
    "monitoring_suggestions": [
        {
            "title": "Performance Metrics",
            "description": "Establish clear metrics to track educational outcomes and program effectiveness."
        },
        {
            "title": "Feedback Systems",
            "description": "Create robust feedback mechanisms to gather input from students, teachers, and parents."
        }
    ]
} 